{"nodes": [{"id": "multi_roi_node", "label": "multi_roi_node.h", "file_type": "code", "source_file": "aicore\\include\\patchcore\\multi_roi_node.h", "source_location": "L1"}, {"id": "multi_roi_node_aicore", "label": "aicore()", "file_type": "code", "source_file": "aicore\\include\\patchcore\\multi_roi_node.h", "source_location": "L15"}], "edges": [{"source": "multi_roi_node", "target": "processor", "relation": "imports", "confidence": "EXTRACTED", "source_file": "aicore\\include\\patchcore\\multi_roi_node.h", "source_location": "L8", "weight": 1.0}, {"source": "multi_roi_node", "target": "memory_bank", "relation": "imports", "confidence": "EXTRACTED", "source_file": "aicore\\include\\patchcore\\multi_roi_node.h", "source_location": "L9", "weight": 1.0}, {"source": "multi_roi_node", "target": "backbone", "relation": "imports", "confidence": "EXTRACTED", "source_file": "aicore\\include\\patchcore\\multi_roi_node.h", "source_location": "L10", "weight": 1.0}, {"source": "multi_roi_node", "target": "roi_def", "relation": "imports", "confidence": "EXTRACTED", "source_file": "aicore\\include\\patchcore\\multi_roi_node.h", "source_location": "L11", "weight": 1.0}, {"source": "multi_roi_node", "target": "vector", "relation": "imports", "confidence": "EXTRACTED", "source_file": "aicore\\include\\patchcore\\multi_roi_node.h", "source_location": "L12", "weight": 1.0}, {"source": "multi_roi_node", "target": "memory", "relation": "imports", "confidence": "EXTRACTED", "source_file": "aicore\\include\\patchcore\\multi_roi_node.h", "source_location": "L13", "weight": 1.0}, {"source": "multi_roi_node", "target": "multi_roi_node_aicore", "relation": "contains", "confidence": "EXTRACTED", "source_file": "aicore\\include\\patchcore\\multi_roi_node.h", "source_location": "L15", "weight": 1.0}]}